{
  "connection": "default",
  "collectionName": "projet",
  "info": {
    "name": "projet",
    "description": ""
  },
  "options": {
    "timestamps": [
      "createdAt",
      "updatedAt"
    ]
  },
  "attributes": {
    "Titre_FR": {
      "type": "string",
      "required": true
    },
    "Contenu_FR": {
      "type": "text"
    },
    "Image": {
      "model": "file",
      "via": "related",
      "plugin": "upload"
    },
    "Contenu_EN": {
      "type": "text"
    },
    "Titre_EN": {
      "required": true,
      "type": "string"
    },
    "Slug_EN": {
      "required": true,
      "type": "string"
    },
    "Audio": {
      "collection": "file",
      "via": "related",
      "plugin": "upload"
    },
    "Soundcloud": {
      "type": "string"
    },
    "categorie": {
      "model": "categorie"
    },
    "Annee": {
      "type": "integer",
      "required": true
    },
    "Slug_FR": {
      "required": true,
      "type": "string"
    },
    "Description_Img_FR": {
      "required": true,
      "maxLength": 125,
      "type": "string"
    },
    "Description_Img_EN": {
      "required": true,
      "maxLength": 125,
      "type": "string"
    },
    "Titre_Img_FR": {
      "maxLength": 64,
      "required": true,
      "type": "string"
    },
    "Titre_Img_EN": {
      "maxLength": 64,
      "required": true,
      "type": "string"
    },
    "Description_FR": {
      "required": true,
      "maxLength": 160,
      "type": "text",
      "default": ""
    },
    "Description_EN": {
      "maxLength": 160,
      "required": true,
      "type": "text"
    }
  }
}